LICENSE
MANIFEST.in
README.rst
setup.py
evdev/__init__.py
evdev/_ecodes.py
evdev/_input.py
evdev/_uinput.py
evdev/device.py
evdev/ecodes.c
evdev/ecodes.py
evdev/ecodes.sh
evdev/events.py
evdev/ff.py
evdev/genecodes.py
evdev/input.c
evdev/uinput.c
evdev/uinput.py
evdev/util.py
evdev.egg-info/PKG-INFO
evdev.egg-info/SOURCES.txt
evdev.egg-info/dependency_links.txt
evdev.egg-info/top_level.txt
evdev.egg-info/zip-safe