Metadata-Version: 1.1
Name: evdev
Version: 0.4.4
Summary: Bindings for the linux input handling subsystem
Home-page: https://github.com/gvalkov/python-evdev
Author: Georgi Valkov
Author-email: georgi.t.valkov@gmail.com
License: Revised BSD License
Keywords: evdev input uinput
Platform: UNKNOWN
Classifier: Development Status :: 5 - Production/Stable
Classifier: Programming Language :: Python :: 2.7
Classifier: Programming Language :: Python :: 3
Classifier: Programming Language :: Python :: 3.2
Classifier: Programming Language :: Python :: 3.3
Classifier: Operating System :: POSIX :: Linux
Classifier: Intended Audience :: Developers
Classifier: Topic :: Software Development :: Libraries
Classifier: License :: OSI Approved :: BSD License
Classifier: Programming Language :: Python :: Implementation :: CPython
